auto_dashboards/__init__.py
auto_dashboards/_version.py
auto_dashboards/handlers.py
auto_dashboards/process_manager.py
auto_dashboards/prompts.py
auto_dashboards/labextension/build_log.json
auto_dashboards/labextension/package.json
auto_dashboards/labextension/static/lib_index_js.4278dad6cf4abcdb28cf.js
auto_dashboards/labextension/static/lib_index_js.4278dad6cf4abcdb28cf.js.map
auto_dashboards/labextension/static/remoteEntry.6c863b7c7b23ad661b87.js
auto_dashboards/labextension/static/remoteEntry.6c863b7c7b23ad661b87.js.map
auto_dashboards/labextension/static/style.js
auto_dashboards/labextension/static/style_index_js.2c9de50a89c2bdfa4eb1.js
auto_dashboards/labextension/static/style_index_js.2c9de50a89c2bdfa4eb1.js.map
auto_dashboards/labextension/static/vendors-node_modules_path-browserify_index_js.abd811c3deacc7fddbf4.js
auto_dashboards/labextension/static/vendors-node_modules_path-browserify_index_js.abd811c3deacc7fddbf4.js.map
auto_dashboards-0.2.1.data/data/etc/jupyter/jupyter_notebook_config.d/auto_dashboards.json
auto_dashboards-0.2.1.data/data/etc/jupyter/jupyter_server_config.d/auto_dashboards.json
auto_dashboards-0.2.1.data/data/share/jupyter/labextensions/@orbrx/auto-dashboards/build_log.json
auto_dashboards-0.2.1.data/data/share/jupyter/labextensions/@orbrx/auto-dashboards/install.json
auto_dashboards-0.2.1.data/data/share/jupyter/labextensions/@orbrx/auto-dashboards/package.json
auto_dashboards-0.2.1.data/data/share/jupyter/labextensions/@orbrx/auto-dashboards/static/lib_index_js.4278dad6cf4abcdb28cf.js
auto_dashboards-0.2.1.data/data/share/jupyter/labextensions/@orbrx/auto-dashboards/static/lib_index_js.4278dad6cf4abcdb28cf.js.map
auto_dashboards-0.2.1.data/data/share/jupyter/labextensions/@orbrx/auto-dashboards/static/remoteEntry.6c863b7c7b23ad661b87.js
auto_dashboards-0.2.1.data/data/share/jupyter/labextensions/@orbrx/auto-dashboards/static/remoteEntry.6c863b7c7b23ad661b87.js.map
auto_dashboards-0.2.1.dist-info/licenses/LICENSE
auto_dashboards-0.2.1.dist-info/METADATA
auto_dashboards-0.2.1.dist-info/WHEEL
auto_dashboards-0.2.1.dist-info/top_level.txt
auto_dashboards-0.2.1.dist-info/RECORD
