Metadata-Version: 2.4
Name: auto-dashboards
Version: 0.2.1
Summary: Auto convert Jupyter notebooks to dashboards
Home-page: https://github.com/orbrx/auto-dashboards
Author: Orange Bricks
License: Apache-2.0
Keywords: Jupyter,JupyterLab,JupyterLab4
Platform: Linux
Platform: Mac OS X
Platform: Windows
Classifier: License :: OSI Approved :: Apache Software License
Classifier: Programming Language :: Python
Classifier: Programming Language :: Python :: 3
Classifier: Programming Language :: Python :: 3.9
Classifier: Programming Language :: Python :: 3.10
Classifier: Programming Language :: Python :: 3.11
Classifier: Programming Language :: Python :: 3.12
Classifier: Framework :: Jupyter
Classifier: Framework :: Jupyter :: JupyterLab
Classifier: Framework :: Jupyter :: JupyterLab :: 3
Classifier: Framework :: Jupyter :: JupyterLab :: Extensions
Classifier: Framework :: Jupyter :: JupyterLab :: Extensions :: Prebuilt
Requires-Python: >=3.9
License-File: LICENSE
Requires-Dist: jupyter_server<3,>=2
Requires-Dist: jupyter-server-proxy
Requires-Dist: streamlit
Requires-Dist: solara
Requires-Dist: nbformat
Requires-Dist: openai
Dynamic: author
Dynamic: classifier
Dynamic: description
Dynamic: description-content-type
Dynamic: home-page
Dynamic: keywords
Dynamic: license
Dynamic: license-file
Dynamic: platform
Dynamic: requires-dist
Dynamic: requires-python
Dynamic: summary
